all_nodes/__init__.py
all_nodes/constants.py
all_nodes/main.py
all_nodes/utils.py
all_nodes/analytics/__init__.py
all_nodes/analytics/analytics.py
all_nodes/graphic/__init__.py
all_nodes/graphic/graphic_annotation.py
all_nodes/graphic/graphic_node.py
all_nodes/graphic/graphic_scene.py
all_nodes/graphic/general_graphics/gears.svg
all_nodes/graphic/general_graphics/hand.svg
all_nodes/graphic/general_graphics/long_tag.svg
all_nodes/graphic/general_graphics/note.svg
all_nodes/graphic/general_graphics/notepad.svg
all_nodes/graphic/general_graphics/pencil.svg
all_nodes/graphic/general_graphics/post_it.svg
all_nodes/graphic/general_graphics/separator.svg
all_nodes/graphic/general_graphics/short_tag.svg
all_nodes/graphic/general_graphics/warning.svg
all_nodes/graphic/general_icons/back.svg
all_nodes/graphic/general_icons/badges.svg
all_nodes/graphic/general_icons/brain.png
all_nodes/graphic/general_icons/clear.png
all_nodes/graphic/general_icons/clipboard.svg
all_nodes/graphic/general_icons/close.svg
all_nodes/graphic/general_icons/ctx.svg
all_nodes/graphic/general_icons/cube.svg
all_nodes/graphic/general_icons/cubes.svg
all_nodes/graphic/general_icons/date.svg
all_nodes/graphic/general_icons/debug.svg
all_nodes/graphic/general_icons/dice.svg
all_nodes/graphic/general_icons/examine.png
all_nodes/graphic/general_icons/expand.png
all_nodes/graphic/general_icons/expand.svg
all_nodes/graphic/general_icons/eye.svg
all_nodes/graphic/general_icons/fail.svg
all_nodes/graphic/general_icons/file.svg
all_nodes/graphic/general_icons/float.svg
all_nodes/graphic/general_icons/folder.svg
all_nodes/graphic/general_icons/front.svg
all_nodes/graphic/general_icons/image.svg
all_nodes/graphic/general_icons/input.svg
all_nodes/graphic/general_icons/load.png
all_nodes/graphic/general_icons/nodes.svg
all_nodes/graphic/general_icons/nodes_2.png
all_nodes/graphic/general_icons/plus.svg
all_nodes/graphic/general_icons/polars.svg
all_nodes/graphic/general_icons/python.svg
all_nodes-1.17.0.dist-info/LICENSE
all_nodes-1.17.0.dist-info/METADATA
all_nodes-1.17.0.dist-info/WHEEL
all_nodes-1.17.0.dist-info/entry_points.txt
all_nodes-1.17.0.dist-info/top_level.txt
all_nodes-1.17.0.dist-info/RECORD
