Metadata-Version: 2.1
Name: all-nodes
Version: 1.17.0
Summary: PySide2-based visual programming for Python 3
Home-page: https://github.com/jaimervq/all_nodes
Author: Jaime Rivera
Author-email: git@jaimervq.se
License: MIT license
Project-URL: Source Repository, https://github.com/jaimervq/all_nodes
Project-URL: Documentation, https://github.com/jaimervq/all_nodes/blob/main/README.md
Classifier: Operating System :: OS Independent
Classifier: Programming Language :: Python :: 3.10
Requires-Python: ==3.10.*
License-File: LICENSE
Requires-Dist: colorama
Requires-Dist: numpy<2
Requires-Dist: matplotlib<3.9
Requires-Dist: Pillow
Requires-Dist: PySide2<6
Requires-Dist: PyYAML==6.*
Requires-Dist: polars==1.3.*
Requires-Dist: pymongo
Requires-Dist: ruff<1
Requires-Dist: toml
